pyoverleaf/__init__.py
pyoverleaf/__main__.py
pyoverleaf/_io.py
pyoverleaf/_version.py
pyoverleaf/_webapi.py
pyoverleaf-0.1.7.dist-info/licenses/LICENSE
pyoverleaf-0.1.7.dist-info/METADATA
pyoverleaf-0.1.7.dist-info/WHEEL
pyoverleaf-0.1.7.dist-info/entry_points.txt
pyoverleaf-0.1.7.dist-info/top_level.txt
pyoverleaf-0.1.7.dist-info/RECORD
