Metadata-Version: 2.4
Name: pyoverleaf
Version: 0.1.7
Summary: Overleaf API and simple CLI
Author-email: Jonas Kulhanek <jonas.kulhanek@live.com>
License-Expression: MIT
Keywords: overleaf,api
Classifier: Programming Language :: Python :: 3
Requires-Python: >=3.8
License-File: LICENSE
Requires-Dist: requests
Requires-Dist: beautifulsoup4
Requires-Dist: browsercookie
Requires-Dist: websocket-client
Requires-Dist: click
Dynamic: license-file
